netbox_tenant_group_permissions_synchronization/__init__.py
netbox_tenant_group_permissions_synchronization/_version.py
netbox_tenant_group_permissions_synchronization/forms.py
netbox_tenant_group_permissions_synchronization/template_content.py
netbox_tenant_group_permissions_synchronization/urls.py
netbox_tenant_group_permissions_synchronization/utils.py
netbox_tenant_group_permissions_synchronization/views.py
netbox_tenant_group_permissions_synchronization/templates/netbox_tenant_group_permissions_synchronization/device_permissions_sync.html
netbox_tenant_group_permissions_synchronization/templates/netbox_tenant_group_permissions_synchronization/sync_device_permissions_button.html
netbox_tenant_group_permissions_synchronization-0.0.3.dist-info/licenses/LICENSE
netbox_tenant_group_permissions_synchronization-0.0.3.dist-info/METADATA
netbox_tenant_group_permissions_synchronization-0.0.3.dist-info/WHEEL
netbox_tenant_group_permissions_synchronization-0.0.3.dist-info/top_level.txt
netbox_tenant_group_permissions_synchronization-0.0.3.dist-info/RECORD
