Metadata-Version: 2.4
Name: netbox_tenant_group_permissions_synchronization
Version: 0.0.3
Summary: Sync tenant_group_permissions from Device to its components in NetBox
Author: Loris Henrion
Author-email: loris_henrion@bce.lu
License: GPL-3.0
License-File: LICENSE
Dynamic: author
Dynamic: author-email
Dynamic: description-content-type
Dynamic: license
Dynamic: license-file
Dynamic: summary
